Metadata-Version: 1.1
Name: skype-chat-history
Version: 0.0.3
Summary: Skype Chat History Extractor
Home-page: http://www.pythoncasovi.com
Author: Darko Dekan
Author-email: darko.dekan@protonmail.com
License: The Unlicense (Unlicense)
Keywords: skype,chat,history,parse,extract,json
Platform: UNKNOWN
Classifier: Development Status :: 5 - Production/Stable
Classifier: Intended Audience :: Developers
Classifier: Operating System :: POSIX :: Linux
Classifier: License :: OSI Approved :: The Unlicense (Unlicense)
Classifier: Programming Language :: Python :: 3.9
